anki_card_cleaner/__init__.py
anki_card_cleaner-0.0.1.dist-info/LICENSE
anki_card_cleaner-0.0.1.dist-info/METADATA
anki_card_cleaner-0.0.1.dist-info/WHEEL
anki_card_cleaner-0.0.1.dist-info/top_level.txt
anki_card_cleaner-0.0.1.dist-info/RECORD
